Proofreader/__init__.py
Proofreader/main.py
Proofreader_polymerase-0.1.0.dist-info/LICENSE.txt
Proofreader_polymerase-0.1.0.dist-info/METADATA
Proofreader_polymerase-0.1.0.dist-info/WHEEL
Proofreader_polymerase-0.1.0.dist-info/entry_points.txt
Proofreader_polymerase-0.1.0.dist-info/top_level.txt
Proofreader_polymerase-0.1.0.dist-info/RECORD
