Metadata-Version: 2.1
Name: Proofreader-polymerase
Version: 0.1.0
Summary: DNA proofreading
Home-page: https://github.com/bichanna/Proofreader-polymerase
Author: bichanna
Author-email: nobu.bichanna@gmail.com
License: MIT
Keywords: DNA,proofread,proofreading,proofreader,python,polymerase
Platform: UNKNOWN
Classifier: Intended Audience :: Education
